Comet/__init__.py
Comet/__main__.py
Comet/hgmd.py
Comet/quads.py
Comet/qvalue.py
Comet/visualize.py
COMETSC-0.1.13.dist-info/LICENSE
COMETSC-0.1.13.dist-info/METADATA
COMETSC-0.1.13.dist-info/WHEEL
COMETSC-0.1.13.dist-info/entry_points.txt
COMETSC-0.1.13.dist-info/top_level.txt
COMETSC-0.1.13.dist-info/RECORD
